blending_toolkit-1.0.9.dist-info/licenses/LICENSE
btk/__init__.py
btk/blend_batch.py
btk/blend_generator.py
btk/catalog.py
btk/deblend.py
btk/draw_blends.py
btk/match.py
btk/measure.py
btk/multiprocess.py
btk/plotting.py
btk/sampling_functions.py
btk/survey.py
btk/utils.py
btk/metrics/__init__.py
btk/metrics/base.py
btk/metrics/detection.py
btk/metrics/reconstruction.py
btk/metrics/segmentation.py
btk/metrics/utils.py
blending_toolkit-1.0.9.dist-info/METADATA
blending_toolkit-1.0.9.dist-info/WHEEL
blending_toolkit-1.0.9.dist-info/top_level.txt
blending_toolkit-1.0.9.dist-info/RECORD
