Metadata-Version: 2.4
Name: blending_toolkit
Version: 1.0.9
Summary: Blending ToolKit
Author: Thomas Sainrat, Andrii Torychlo, Somwya Kamath, Maxime Paillasa, Alexandre Boucaud, Biswajit Biswas, Prakruth Adari, Remy Joseph, Patricia Burchat, Cyrille Doux, Eric Aubourg
Maintainer-email: Ismael Mendoza <imendoza@umich.edu>
License: MIT License
Project-URL: Homepage, https://lsstdesc.org/BlendingToolKit/index.html
Project-URL: Repository, https://github.com/LSSTDESC/BlendingToolKit
Project-URL: Bug Tracker, https://github.com/LSSTDESC/BlendingToolKit/issues
Keywords: cosmology,galaxies,blending,lsst,simulation
Classifier: Programming Language :: Python :: 3.9
Classifier: Programming Language :: Python :: 3.10
Classifier: Programming Language :: Python :: 3.11
Classifier: Programming Language :: Python :: 3.12
Classifier: License :: OSI Approved :: MIT License
Classifier: Operating System :: OS Independent
Requires-Python: <3.13,>=3.9
License-File: LICENSE
Requires-Dist: galsim>=2.4.9
Requires-Dist: sep>=1.4.0
Requires-Dist: surveycodex>=1.2.0
Requires-Dist: numpy>=1.26.0
Requires-Dist: fast3tree>=0.4.1
Requires-Dist: scipy>=1.13.1
Requires-Dist: scikit-image>=0.24.0
Requires-Dist: h5py>=3.12.1
Requires-Dist: tqdm>=4.67.1
Requires-Dist: astropy<7.0.0,>=5.1.0
Requires-Dist: matplotlib>=3.7.0
Provides-Extra: dev
Requires-Dist: jupyter>=1.1.1; extra == "dev"
Requires-Dist: jupyter-sphinx>=0.4.0; extra == "dev"
Requires-Dist: nbmake>=1.5.5; extra == "dev"
Requires-Dist: nbstripout>=0.8.1; extra == "dev"
Requires-Dist: pre-commit>=4.0.1; extra == "dev"
Requires-Dist: pytest>=8.3.4; extra == "dev"
Requires-Dist: pytest-cov>=6.0.0; extra == "dev"
Requires-Dist: ruff>=0.9.1; extra == "dev"
Requires-Dist: sphinx>=7.4.7; extra == "dev"
Requires-Dist: sphinx-rtd-theme>=1.2.1; extra == "dev"
Provides-Extra: scarlet
Requires-Dist: peigen>=0.0.9; extra == "scarlet"
Requires-Dist: autograd>=1.5.0; extra == "scarlet"
Requires-Dist: proxmin>=0.6.12; extra == "scarlet"
Requires-Dist: pybind11>=2.10.3; extra == "scarlet"
Dynamic: license-file
